Metadata-Version: 2.4
Name: monitorch
Version: 0.0.2.0
Summary: A plug-and-use python library to monitor learning of PyTorch neural networks
Author-email: Maksym Khavil <mk.khavil@gmail.com>
License-Expression: BSD-3-Clause
Project-URL: Homepage, https://github.com/ZhigaMason/monitorch
Project-URL: Bug Tracker, https://github.com/ZhigaMason/monitorch/issues
Keywords: pytorch,visualization,neural networks,gradients
Classifier: Programming Language :: Python :: 3
Classifier: Operating System :: OS Independent
Requires-Python: >=3.10
License-File: LICENSE
Requires-Dist: torch>=2.0.0
Requires-Dist: matplotlib>=3.10.0
Requires-Dist: tensorboard>=2.19.0
Dynamic: license-file
